Metadata-Version: 1.1
Name: dummy-spark
Version: 0.0.1
Summary: A pure python mocked version of pyspark's rdd class
Home-page: https://github.com/wdm0006/dummyrdd
Author: Will McGinnis
Author-email: will@pedalwrencher.com
License: MIT
Download-URL: https://github.com/wdm0006/dummyrdd/tarball/0.0.1
Keywords: pyspark spark testing
Platform: UNKNOWN
Classifier: Development Status :: 3 - Alpha
Classifier: Intended Audience :: Developers
Classifier: Programming Language :: Python :: 3
